llama_index/embeddings/modelscope/__init__.py
llama_index/embeddings/modelscope/base.py
llama_index/embeddings/modelscope/utils.py
llama_index_embeddings_modelscope-0.5.1.dist-info/METADATA
llama_index_embeddings_modelscope-0.5.1.dist-info/WHEEL
llama_index_embeddings_modelscope-0.5.1.dist-info/licenses/LICENSE
llama_index_embeddings_modelscope-0.5.1.dist-info/RECORD
