Metadata-Version: 2.4
Name: llama-index-embeddings-modelscope
Version: 0.5.1
Summary: llama-index embeddings modelscope integration
Author-email: ModelScope <modelscope@list.alibaba-inc.com>
License-Expression: MIT
License-File: LICENSE
Requires-Python: <3.12,>=3.9
Requires-Dist: llama-index-core<0.15,>=0.13.0
Requires-Dist: modelscope[framework]>=1.12.0
Requires-Dist: ms-swift
Requires-Dist: sentencepiece
Requires-Dist: torch<3,>=2.1.2
Requires-Dist: transformers[torch]<5,>=4.37.0
